setup.py
src/deepfreeze/__init__.py
src/deepfreeze.egg-info/PKG-INFO
src/deepfreeze.egg-info/SOURCES.txt
src/deepfreeze.egg-info/dependency_links.txt
src/deepfreeze.egg-info/entry_points.txt
src/deepfreeze.egg-info/requires.txt
src/deepfreeze.egg-info/top_level.txt