Metadata-Version: 1.1
Name: deepfreeze
Version: 0.1.1
Summary: A simple command-line utility to upload files to Amazon Glacier.
Home-page: https://github.com/rfkrocktk/deepfreeze
Author: Naftuli Tzvi Kay
Author-email: rfkrocktk@gmail.com
License: UNKNOWN
Download-URL: https://github.com/rfkrocktk/deepfreeze/releases
Platform: UNKNOWN
Classifier: Environment :: Console
Classifier: Intended Audience :: Developers
Classifier: Intended Audience :: System Administrators
Classifier: Operating System :: MacOS :: MacOS X
Classifier: Operating System :: POSIX
Classifier: Operating System :: Unix
Classifier: Programming Language :: Python
Classifier: Programming Language :: Python :: 2.7
Classifier: Topic :: System :: Systems Administration
